AUTHORS.rst
CONTRIBUTING.rst
HISTORY.rst
LICENSE
MANIFEST.in
README.rst
setup.cfg
setup.py
docs/authors.rst
docs/conf.py
docs/contributing.rst
docs/history.rst
docs/index.rst
docs/installation.rst
docs/readme.rst
docs/usage.rst
pep582/__init__.py
pep582/cli.py
pep582/patch.py
pep582/site.py
pep582.egg-info/PKG-INFO
pep582.egg-info/SOURCES.txt
pep582.egg-info/dependency_links.txt
pep582.egg-info/entry_points.txt
pep582.egg-info/not-zip-safe
pep582.egg-info/requires.txt
pep582.egg-info/top_level.txt
tests/__init__.py
tests/test_pep582.py